py_grpc_prometheus/__init__.py
py_grpc_prometheus/client_metrics.py
py_grpc_prometheus/grpc_utils.py
py_grpc_prometheus/prometheus_client_interceptor.py
py_grpc_prometheus/prometheus_server_interceptor.py
py_grpc_prometheus/server_metrics.py
py_grpc_prometheus-0.7.0.dist-info/LICENSE
py_grpc_prometheus-0.7.0.dist-info/METADATA
py_grpc_prometheus-0.7.0.dist-info/WHEEL
py_grpc_prometheus-0.7.0.dist-info/top_level.txt
py_grpc_prometheus-0.7.0.dist-info/RECORD
