Metadata-Version: 2.1
Name: py_grpc_prometheus
Version: 0.7.0
Summary: Python gRPC Prometheus Interceptors
Home-page: https://github.com/lchenn/py-grpc-prometheus
Author: Lin Chen
Author-email: linchen04@gmail.com
License: UNKNOWN
Platform: UNKNOWN
